db_diagram/__init__.py
db_diagram/__main__.py
db_diagram/_databricks.py
db_diagram/_mermaid.py
db_diagram/_utilities.py
db_diagram/py.typed
db_diagram-0.0.1.dist-info/METADATA
db_diagram-0.0.1.dist-info/WHEEL
db_diagram-0.0.1.dist-info/entry_points.txt
db_diagram-0.0.1.dist-info/RECORD
