Metadata-Version: 2.4
Name: db-diagram
Version: 0.0.1
Summary: Create Database Entity Relationship Diagrams
Project-URL: Documentation, https://db-diagram.enorganic.org
Project-URL: Repository, https://github.com/enorganic/db-diagram
Author-email: david@belais.me
License-Expression: MIT
Keywords: database,diagram
Requires-Python: ~=3.10
Requires-Dist: sqlalchemy~=2.0
Provides-Extra: databricks
Requires-Dist: databricks-sqlalchemy~=2.0; extra == 'databricks'
Provides-Extra: postgresql
Requires-Dist: psycopg~=3.3; extra == 'postgresql'
Provides-Extra: snowflake
Requires-Dist: snowflake-sqlalchemy~=1.8; extra == 'snowflake'
